opentypespec/__init__.py
opentypespec/tags/__init__.py
opentypespec/tags/features.py
opentypespec/tags/languages.py
opentypespec/tags/scripts.py
opentypespec-1.8.4.dist-info/LICENSE
opentypespec-1.8.4.dist-info/METADATA
opentypespec-1.8.4.dist-info/WHEEL
opentypespec-1.8.4.dist-info/top_level.txt
opentypespec-1.8.4.dist-info/RECORD
